{ "serviceId": "1", "name": "scalp analysis with treatment", "price": "45.00$", "link": "scalpAnalysisWithTreatment", "description": "Scalp analysis with treatment"}
{ "serviceId": "2", "name": "hairline", "price": "10.00$", "link": "hairline", "description": "Hairlines"}
{ "serviceId": "3", "name": "Children haircuts", "price": "45.00$", "link": "childrenHaircuts", "description": "Children haircuts"}
{ "serviceId": "4", "name": "hairline with razor", "price": "15.00$", "link": "hairlineWithRazor", "description": "Hairline with razor"}
{ "serviceId": "5", "name": "Men regular haircut", "price": "20.00$", "link": "menRegularHaircut", "description": "Men regular haircut"}
{ "serviceId": "6", "name": "Woman haircut", "price": "25.00$", "link": "womanHaircut", "description": "Woman haircut"}
{ "serviceId": "7", "name": "men's afro haircuts", "price": "25.00$", "link": "mensAfroHaircuts", "description": "Men's afro haircuts"}
{ "serviceId": "8", "name": "haircut & Shampoo", "price": "25.00$", "link": "haircutAndShampoo", "description": "Haircut and shampoo"}
{ "serviceId": "9", "name": "afro haircut with wash", "price": "30.00$", "link": "afroHaircutWithWash", "description": "Afro haircut with wash"}
{ "serviceId": "10", "name": "haircut shampoo & condition", "price": "30.00$", "link": "haircutShampooAndCondition", "description": "Haircut shampoo and condition"}
{ "serviceId": "11", "name": "Eyebrows", "price": "8.00$", "link": "eyebrows", "description": "this service is done with a razor"}
{ "serviceId": "12", "name": "private VIP cutting room", "price": "100.00$", "link": "privateVipCuttingRoom", "description": "haircut in VIP status for none members & up with all the amenities. HDTV with over 500 channels, stero surround sound, X-box 360, business center for you & your guest, complimentary beverages, appetizers & H'orderves. must book 24hr in advance"}